controlplus/__init__.py
controlplus/controlplus.py
controlplus-0.2.0.dist-info/LICENSE
controlplus-0.2.0.dist-info/WHEEL
controlplus-0.2.0.dist-info/METADATA
controlplus-0.2.0.dist-info/RECORD
