Metadata-Version: 2.1
Name: controlplus
Version: 0.2.0
Summary: A package for analysis and design of Control Systems in python.
Home-page: https://controlplus.readthedocs.io/en/latest/
License: GNU General Public License v3.0
Author: Dr. Ahsen Tahir
Requires-Python: >=3.9
Classifier: License :: Other/Proprietary License
Classifier: Programming Language :: Python :: 3
Classifier: Programming Language :: Python :: 3.10
Classifier: Programming Language :: Python :: 3.9
Requires-Dist: control (>=0.9.2)
Requires-Dist: matplotlib (>=3.6.2)
Requires-Dist: numpy (>=1.23.5)
